azure/ml/__init__.py
azure/ml/component/__init__.py
azure/ml/component/_aml_core_dependencies.py
azure/ml/component/_component_func.py
azure/ml/component/_component_validator.py
azure/ml/component/_constants.py
azure/ml/component/_dataset.py
azure/ml/component/_dynamic.py
azure/ml/component/_endpoint.py
azure/ml/component/_graph.py
azure/ml/component/_graph_to_code.py
azure/ml/component/_module_dto.py
azure/ml/component/_parameter_assignment.py
azure/ml/component/_pipeline_component_definition_builder.py
azure/ml/component/_pipeline_export_provider.py
azure/ml/component/_pipeline_expression.py
azure/ml/component/_pipeline_parameters.py
azure/ml/component/_pipeline_validator.py
azure/ml/component/_published_pipeline.py
azure/ml/component/_run_settings_contracts.py
azure/ml/component/_sub_pipeline_info_builder.py
azure/ml/component/_version.py
azure/ml/component/_visible.py
azure/ml/component/_visualization_context.py
azure/ml/component/component.py
azure/ml/component/environment.py
azure/ml/component/pipeline.py
azure/ml/component/run.py
azure/ml/component/run_settings.py
azure/ml/component/_api/__init__.py
azure/ml/component/_api/_api.py
azure/ml/component/_api/_api_impl.py
azure/ml/component/_api/_component_snapshot.py
azure/ml/component/_api/_component_source.py
azure/ml/component/_api/_snapshot_cache.py
azure/ml/component/_api/_snapshots_client.py
azure/ml/component/_api/_snapshots_client_core.py
azure/ml/component/_api/_utils.py
azure/ml/component/_cli/__init__.py
azure/ml/component/_cli/az_ml_command.py
azure/ml/component/_cli/component_commands.py
azure/ml/component/_cli/component_subgroup.py
azure/ml/component/_cli/status_indicator.py
azure/ml/component/_cli/transformers.py
azure/ml/component/_cli/utils.py
azure/ml/component/_core/__init__.py
azure/ml/component/_core/_component_contexts.py
azure/ml/component/_core/_component_definition.py
azure/ml/component/_core/_core.py
azure/ml/component/_core/_environment.py
azure_ml_component-0.9.18.post2.dist-info/LICENSE.txt
azure_ml_component-0.9.18.post2.dist-info/METADATA
azure_ml_component-0.9.18.post2.dist-info/WHEEL
azure_ml_component-0.9.18.post2.dist-info/entry_points.txt
azure_ml_component-0.9.18.post2.dist-info/top_level.txt
azure_ml_component-0.9.18.post2.dist-info/RECORD
